setup.py
flask_project_restful/__init__.py
flask_project_restful/container.py
flask_project_restful/convertion.py
flask_project_restful/logic.py
flask_project_restful/scanner.py
flask_project_restful.egg-info/PKG-INFO
flask_project_restful.egg-info/SOURCES.txt
flask_project_restful.egg-info/dependency_links.txt
flask_project_restful.egg-info/requires.txt
flask_project_restful.egg-info/top_level.txt