Metadata-Version: 2.1
Name: flask-project-restful
Version: 0.0.7
Summary: flask projects系列的restful自定义扩展
Home-page: https://github.com/ababbabbb/flask_project_extends
Author: bichuantao
Author-email: 17826066203@163.com
License: MIT
Keywords: python,flask project,extends,flask_project_restful
Requires-Python: >=3.6
Requires-Dist: flask
Requires-Dist: flask-restful
Requires-Dist: flask-p
